{"Sheet1":[{"Headers":"collection1","HeadersThumbs":"https://github.com/indpgamesandapps/Indian-Saree-Designs/raw/master/Menu_Icons/Saree/collection1.png","HeadersDisplay":"Yes","collection1Thumbs":"","collection1HD":"","collection2Thumbs":"","collection2HD":"","collection3Thumbs":"","collection3HD":"","collection4Thumbs":"","collection4HD":"","collection5Thumbs":"","collection5HD":"","collection6Thumbs":"","collection6HD":"","collection7Thumbs":"","collection7HD":"","collection8Thumbs":"","collection8HD":"","collection9Thumbs":"","collection9HD":"","collection10Thumbs":"","collection10HD":""},{"Headers":"collection2","HeadersThumbs":"https://github.com/indpgamesandapps/Indian-Saree-Designs/raw/master/Menu_Icons/Saree/collection2.png","HeadersDisplay":"Yes","collection1Thumbs":"","collection1HD":"","collection2Thumbs":"","collection2HD":"","collection3Thumbs":"","collection3HD":"","collection4Thumbs":"","collection4HD":"","collection5Thumbs":"","collection5HD":"","collection6Thumbs":"","collection6HD":"","collection7Thumbs":"","collection7HD":"","collection8Thumbs":"","collection8HD":"","collection9Thumbs":"","collection9HD":"","collection10Thumbs":"","collection10HD":""},{"Headers":"collection3","HeadersThumbs":"https://github.com/indpgamesandapps/Indian-Saree-Designs/raw/master/Menu_Icons/Saree/collection3.png","HeadersDisplay":"Yes","collection1Thumbs":"","collection1HD":"","collection2Thumbs":"","collection2HD":"","collection3Thumbs":"","collection3HD":"","collection4Thumbs":"","collection4HD":"","collection5Thumbs":"","collection5HD":"","collection6Thumbs":"","collection6HD":"","collection7Thumbs":"","collection7HD":"","collection8Thumbs":"","collection8HD":"","collection9Thumbs":"","collection9HD":"","collection10Thumbs":"","collection10HD":""},{"Headers":"collection4","HeadersThumbs":"https://github.com/indpgamesandapps/Indian-Saree-Designs/raw/master/Menu_Icons/Saree/collection4.png","HeadersDisplay":"Yes","collection1Thumbs":"","collection1HD":"","collection2Thumbs":"","collection2HD":"","collection3Thumbs":"","collection3HD":"","collection4Thumbs":"","collection4HD":"","collection5Thumbs":"","collection5HD":"","collection6Thumbs":"","collection6HD":"","collection7Thumbs":"","collection7HD":"","collection8Thumbs":"","collection8HD":"","collection9Thumbs":"","collection9HD":"","collection10Thumbs":"","collection10HD":""},{"Headers":"collection5","HeadersThumbs":"https://github.com/indpgamesandapps/Indian-Saree-Designs/raw/master/Menu_Icons/Saree/collection5.png","HeadersDisplay":"Yes","collection1Thumbs":"","collection1HD":"","collection2Thumbs":"","collection2HD":"","collection3Thumbs":"","collection3HD":"","collection4Thumbs":"","collection4HD":"","collection5Thumbs":"","collection5HD":"","collection6Thumbs":"","collection6HD":"","collection7Thumbs":"","collection7HD":"","collection8Thumbs":"","collection8HD":"","collection9Thumbs":"","collection9HD":"","collection10Thumbs":"","collection10HD":""},{"Headers":"collection6","HeadersThumbs":"https://github.com/indpgamesandapps/Indian-Saree-Designs/raw/master/Menu_Icons/Saree/collection6.png","HeadersDisplay":"Yes","collection1Thumbs":"","collection1HD":"","collection2Thumbs":"","collection2HD":"","collection3Thumbs":"","collection3HD":"","collection4Thumbs":"","collection4HD":"","collection5Thumbs":"","collection5HD":"","collection6Thumbs":"","collection6HD":"","collection7Thumbs":"","collection7HD":"","collection8Thumbs":"","collection8HD":"","collection9Thumbs":"","collection9HD":"","collection10Thumbs":"","collection10HD":""},{"Headers":"collection7","HeadersThumbs":"https://github.com/indpgamesandapps/Indian-Saree-Designs/raw/master/Menu_Icons/Saree/collection7.png","HeadersDisplay":"Yes","collection1Thumbs":"","collection1HD":"","collection2Thumbs":"","collection2HD":"","collection3Thumbs":"","collection3HD":"","collection4Thumbs":"","collection4HD":"","collection5Thumbs":"","collection5HD":"","collection6Thumbs":"","collection6HD":"","collection7Thumbs":"","collection7HD":"","collection8Thumbs":"","collection8HD":"","collection9Thumbs":"","collection9HD":"","collection10Thumbs":"","collection10HD":""},{"Headers":"collection8","HeadersThumbs":"https://github.com/indpgamesandapps/Indian-Saree-Designs/raw/master/Menu_Icons/Saree/collection8.png","HeadersDisplay":"Yes","collection1Thumbs":"","collection1HD":"","collection2Thumbs":"","collection2HD":"","collection3Thumbs":"","collection3HD":"","collection4Thumbs":"","collection4HD":"","collection5Thumbs":"","collection5HD":"","collection6Thumbs":"","collection6HD":"","collection7Thumbs":"","collection7HD":"","collection8Thumbs":"","collection8HD":"","collection9Thumbs":"","collection9HD":"","collection10Thumbs":"","collection10HD":""},{"Headers":"collection9","HeadersThumbs":"https://github.com/indpgamesandapps/Indian-Saree-Designs/raw/master/Menu_Icons/Saree/collection9.png","HeadersDisplay":"Yes","collection1Thumbs":"","collection1HD":"","collection2Thumbs":"","collection2HD":"","collection3Thumbs":"","collection3HD":"","collection4Thumbs":"","collection4HD":"","collection5Thumbs":"","collection5HD":"","collection6Thumbs":"","collection6HD":"","collection7Thumbs":"","collection7HD":"","collection8Thumbs":"","collection8HD":"","collection9Thumbs":"","collection9HD":"","collection10Thumbs":"","collection10HD":""},{"Headers":"collection10","HeadersThumbs":"https://github.com/indpgamesandapps/Indian-Saree-Designs/raw/master/Menu_Icons/Saree/collection10.png","HeadersDisplay":"Yes","collection1Thumbs":"","collection1HD":"","collection2Thumbs":"","collection2HD":"","collection3Thumbs":"","collection3HD":"","collection4Thumbs":"","collection4HD":"","collection5Thumbs":"","collection5HD":"","collection6Thumbs":"","collection6HD":"","collection7Thumbs":"","collection7HD":"","collection8Thumbs":"","collection8HD":"","collection9Thumbs":"","collection9HD":"","collection10Thumbs":"","collection10HD":""}]}